easy_selenium_automation/__init__.py
easy_selenium_automation/selenium_utils.py
easy_selenium_automation-0.3.dist-info/LICENSE
easy_selenium_automation-0.3.dist-info/METADATA
easy_selenium_automation-0.3.dist-info/WHEEL
easy_selenium_automation-0.3.dist-info/top_level.txt
easy_selenium_automation-0.3.dist-info/RECORD
