Metadata-Version: 2.1
Name: easy-selenium-automation
Version: 0.3
Summary: A simple library to simplify Selenium automations.
Home-page: https://github.com/tondevpy
Author: TonDevPy
License: MIT
Classifier: Programming Language :: Python :: 3
Classifier: License :: OSI Approved :: MIT License
Classifier: Operating System :: OS Independent
Requires-Python: >=3.6
License-File: LICENSE
Requires-Dist: selenium
